rpft/__init__.py
rpft/cli.py
rpft/converters.py
rpft/google.py
rpft/sources.py
rpft/logger/__init__.py
rpft/logger/logger.py
rpft/parsers/__init__.py
rpft/parsers/sheets.py
rpft/parsers/universal.py
rpft/parsers/common/__init__.py
rpft/parsers/common/cellparser.py
rpft/parsers/common/model_inference.py
rpft/parsers/common/rowdatasheet.py
rpft/parsers/common/rowparser.py
rpft/parsers/common/sheetparser.py
rpft/parsers/creation/__init__.py
rpft/parsers/creation/campaigneventrowmodel.py
rpft/parsers/creation/campaignparser.py
rpft/parsers/creation/constants.py
rpft/parsers/creation/contentindexparser.py
rpft/parsers/creation/contentindexrowmodel.py
rpft/parsers/creation/datarowmodel.py
rpft/parsers/creation/flowparser.py
rpft/parsers/creation/flowrowmodel.py
rpft/parsers/creation/globalrowmodels.py
rpft/parsers/creation/models.py
rpft/parsers/creation/surveyparser.py
rpft/parsers/creation/tagmatcher.py
rpft/parsers/creation/triggerparser.py
rpft/parsers/creation/triggerrowmodel.py
rpft/rapidpro/__init__.py
rpft/rapidpro/simulation.py
rpft/rapidpro/utils.py
rpft/rapidpro/models/__init__.py
rpft/rapidpro/models/actions.py
rpft/rapidpro/models/campaigns.py
rpft/rapidpro/models/common.py
rpft/rapidpro/models/containers.py
rpft/rapidpro/models/exceptions.py
rpft/rapidpro/models/nodes.py
rpft/rapidpro/models/routers.py
rpft/rapidpro/models/triggers.py
rpft-1.18.0.dist-info/licenses/LICENSE
rpft-1.18.0.dist-info/METADATA
rpft-1.18.0.dist-info/WHEEL
rpft-1.18.0.dist-info/entry_points.txt
rpft-1.18.0.dist-info/top_level.txt
rpft-1.18.0.dist-info/RECORD
