Metadata-Version: 2.4
Name: rpft
Version: 1.18.0
Summary: Toolkit for using spreadsheets to create and modify RapidPro flows
Author-email: IDEMS International <contact@idems.international>
License-Expression: LGPL-2.1-or-later
Project-URL: Homepage, https://github.com/IDEMSInternational/rapidpro-flow-toolkit
Project-URL: Repository, https://github.com/IDEMSInternational/rapidpro-flow-toolkit
Keywords: rapidpro,flow,tools,toolkit
Classifier: Development Status :: 4 - Beta
Classifier: Environment :: Console
Classifier: Intended Audience :: Developers
Classifier: Operating System :: OS Independent
Classifier: Programming Language :: Python
Classifier: Programming Language :: Python :: 3
Classifier: Programming Language :: Python :: 3 :: Only
Classifier: Programming Language :: Python :: 3.9
Classifier: Programming Language :: Python :: 3.10
Classifier: Programming Language :: Python :: 3.11
Classifier: Programming Language :: Python :: 3.12
Classifier: Programming Language :: Python :: 3.13
Classifier: Topic :: Text Processing :: General
Classifier: Topic :: Utilities
Requires-Python: >=3.9
License-File: LICENSE
Requires-Dist: Jinja2~=3.0.3
Requires-Dist: google-api-python-client~=2.174
Requires-Dist: google-auth-oauthlib~=1.2
Requires-Dist: networkx~=2.5.1
Requires-Dist: odfpy
Requires-Dist: openpyxl
Requires-Dist: pydantic>=2
Requires-Dist: python-benedict
Requires-Dist: tablib~=3.8
Dynamic: license-file
